{"data": {"attributes": {"last_dns_records": [{"type": "NS", "value": "ns1.aezadns.com", "ttl": 3600}, {"type": "A", "value": "185.106.93.93", "ttl": 3600}, {"rname": "support.aeza.net", "retry": 3600, "refresh": 10800, "minimum": 3600, "value": "ns1.aezadns.com", "expire": 604800, "ttl": 3600, "serial": 2023030110, "type": "SOA"}, {"type": "NS", "value": "ns2.aezadns.com", "ttl": 3600}], "jarm": "2ad2ad0002ad2ad00042d42d00000051af7d8070a18e002eaaedf620fa118c", "whois": "Create date: 2023-02-27 00:00:00\nDomain name: loads19421.online\nDomain registrar id: 1068\nDomain registrar url: https://namecheap.com\nExpiry date: 2024-02-27 00:00:00\nName server 1: NS2.AEZADNS.COM\nName server 2: NS1.AEZADNS.COM\nQuery time: 2023-02-28 23:45:52\nRegistrant company: 4b7a0912c26a13e2\nRegistrant country: Iceland\nRegistrant email: c3e4472e8f320a6ds@\nRegistrant state: 3e0204199d8ebf9c\nUpdate date: 2023-02-27 00:00:00", "last_https_certificate_date": 1678267695, "tags": ["dga"], "popularity_ranks": {}, "last_analysis_date": 1678267689, "last_dns_records_date": 1678267695, "last_analysis_stats": {"harmless": 0, "malicious": 0, "suspicious": 0, "undetected": 86, "timeout": 0}, "creation_date": 1677456000, "whois_date": 1708992000, "reputation": 0, "last_analysis_results": {"Bkav": {"category": "undetected", "result": "unrated", "method": "blacklist", "engine_name": "Bkav"}, "CMC Threat Intelligence": {"category": "undetected", "result": "unrated", "method": "blacklist", "engine_name": "CMC Threat Intelligence"}, "Snort IP sample list": {"category": "undetected", "result": "unrated", "method": "blacklist", "engine_name": "Snort IP sample list"}, "0xSI_f33d": {"category": "undetected", "result": "unrated", "method": "blacklist", "engine_name": "0xSI_f33d"}, "ViriBack": {"category": "undetected", "result": "unrated", "method": "blacklist", "engine_name": "ViriBack"}, "PhishLabs": {"category": "undetected", "result": "unrated", "method": "blacklist", "engine_name": "PhishLabs"}, "K7AntiVirus": {"category": "undetected", "result": "unrated", "method": "blacklist", "engine_name": "K7AntiVirus"}, "CINS Army": {"category": "undetected", "result": "unrated", "method": "blacklist", "engine_name": "CINS Army"}, "Quttera": {"category": "undetected", "result": "unrated", "method": "blacklist", "engine_name": "Quttera"}, "PrecisionSec": {"category": "undetected", "result": "unrated", "method": "blacklist", "engine_name": "PrecisionSec"}, "OpenPhish": {"category": "undetected", "result": "unrated", "method": "blacklist", "engine_name": "OpenPhish"}, "VX Vault": {"category": "undetected", "result": "unrated", "method": "blacklist", "engine_name": "VX Vault"}, "ADMINUSLabs": {"category": "undetected", "result": "unrated", "method": "blacklist", "engine_name": "ADMINUSLabs"}, "Scantitan": {"category": "undetected", "result": "unrated", "method": "blacklist", "engine_name": "Scantitan"}, "AlienVault": {"category": "undetected", "result": "unrated", "method": "blacklist", "engine_name": "AlienVault"}, "Sophos": {"category": "undetected", "result": "unrated", "method": "blacklist", "engine_name": "Sophos"}, "Phishtank": {"category": "undetected", "result": "unrated", "method": "blacklist", "engine_name": "Phishtank"}, "ESTsecurity": {"category": "undetected", "result": "unrated", "method": "blacklist", "engine_name": "ESTsecurity"}, "Spam404": {"category": "undetected", "result": "unrated", "method": "blacklist", "engine_name": "Spam404"}, "SecureBrain": {"category": "undetected", "result": "unrated", "method": "blacklist", "engine_name": "SecureBrain"}, "CRDF": {"category": "undetected", "result": "unrated", "method": "blacklist", "engine_name": "CRDF"}, "Fortinet": {"category": "undetected", "result": "unrated", "method": "blacklist", "engine_name": "Fortinet"}, "alphaMountain.ai": {"category": "undetected", "result": "unrated", "method": "blacklist", "engine_name": "alphaMountain.ai"}, "Lionic": {"category": "undetected", "result": "unrated", "method": "blacklist", "engine_name": "Lionic"}, "Cyble": {"category": "undetected", "result": "unrated", "method": "blacklist", "engine_name": "Cyble"}, "Seclookup": {"category": "undetected", "result": "unrated", "method": "blacklist", "engine_name": "Seclookup"}, "Xcitium Verdict Cloud": {"category": "undetected", "result": "unrated", "method": "blacklist", "engine_name": "Xcitium Verdict Cloud"}, "Google Safebrowsing": {"category": "undetected", "result": "unrated", "method": "blacklist", "engine_name": "Google Safebrowsing"}, "SafeToOpen": {"category": "undetected", "result": "unrated", "method": "blacklist", "engine_name": "SafeToOpen"}, "ArcSight Threat Intelligence": {"category": "undetected", "result": "unrated", "method": "blacklist", "engine_name": "ArcSight Threat Intelligence"}, "Cyan": {"category": "undetected", "result": "unrated", "method": "blacklist", "engine_name": "Cyan"}, "Juniper Networks": {"category": "undetected", "result": "unrated", "method": "blacklist", "engine_name": "Juniper Networks"}, "Heimdal Security": {"category": "undetected", "result": "unrated", "method": "blacklist", "engine_name": "Heimdal Security"}, "AutoShun": {"category": "undetected", "result": "unrated", "method": "blacklist", "engine_name": "AutoShun"}, "Trustwave": {"category": "undetected", "result": "unrated", "method": "blacklist", "engine_name": "Trustwave"}, "AICC (MONITORAPP)": {"category": "undetected", "result": "unrated", "method": "blacklist", "engine_name": "AICC (MONITORAPP)"}, "CyRadar": {"category": "undetected", "result": "unrated", "method": "blacklist", "engine_name": "CyRadar"}, "Dr.Web": {"category": "undetected", "result": "unrated", "method": "blacklist", "engine_name": "Dr.Web"}, "Emsisoft": {"category": "undetected", "result": "unrated", "method": "blacklist", "engine_name": "Emsisoft"}, "Abusix": {"category": "undetected", "result": "unrated", "method": "blacklist", "engine_name": "Abusix"}, "Webroot": {"category": "undetected", "result": "unrated", "method": "blacklist", "engine_name": "Webroot"}, "Avira": {"category": "undetected", "result": "unrated", "method": "blacklist", "engine_name": "Avira"}, "securolytics": {"category": "undetected", "result": "unrated", "method": "blacklist", "engine_name": "securolytics"}, "Antiy-AVL": {"category": "undetected", "result": "unrated", "method": "blacklist", "engine_name": "Antiy-AVL"}, "AlphaSOC": {"category": "undetected", "result": "unrated", "method": "blacklist", "engine_name": "AlphaSOC"}, "Acronis": {"category": "undetected", "result": "unrated", "method": "blacklist", "engine_name": "Acronis"}, "Quick Heal": {"category": "undetected", "result": "unrated", "method": "blacklist", "engine_name": "Quick Heal"}, "URLQuery": {"category": "undetected", "result": "unrated", "method": "blacklist", "engine_name": "URLQuery"}, "Viettel Threat Intelligence": {"category": "undetected", "result": "unrated", "method": "blacklist", "engine_name": "Viettel Threat Intelligence"}, "DNS8": {"category": "undetected", "result": "unrated", "method": "blacklist", "engine_name": "DNS8"}, "benkow.cc": {"category": "undetected", "result": "unrated", "method": "blacklist", "engine_name": "benkow.cc"}, "EmergingThreats": {"category": "undetected", "result": "unrated", "method": "blacklist", "engine_name": "EmergingThreats"}, "Chong Lua Dao": {"category": "undetected", "result": "unrated", "method": "blacklist", "engine_name": "Chong Lua Dao"}, "Yandex Safebrowsing": {"category": "undetected", "result": "unrated", "method": "blacklist", "engine_name": "Yandex Safebrowsing"}, "Lumu": {"category": "undetected", "result": "unrated", "method": "blacklist", "engine_name": "Lumu"}, "zvelo": {"category": "undetected", "result": "unrated", "method": "blacklist", "engine_name": "zvelo"}, "Kaspersky": {"category": "undetected", "result": "unrated", "method": "blacklist", "engine_name": "Kaspersky"}, "Segasec": {"category": "undetected", "result": "unrated", "method": "blacklist", "engine_name": "Segasec"}, "Sucuri SiteCheck": {"category": "undetected", "result": "unrated", "method": "blacklist", "engine_name": "Sucuri SiteCheck"}, "desenmascara.me": {"category": "undetected", "result": "unrated", "method": "blacklist", "engine_name": "desenmascara.me"}, "CrowdSec": {"category": "undetected", "result": "unrated", "method": "blacklist", "engine_name": "CrowdSec"}, "Cluster25": {"category": "undetected", "result": "unrated", "method": "blacklist", "engine_name": "Cluster25"}, "URLhaus": {"category": "undetected", "result": "unrated", "method": "blacklist", "engine_name": "URLhaus"}, "PREBYTES": {"category": "undetected", "result": "unrated", "method": "blacklist", "engine_name": "PREBYTES"}, "StopForumSpam": {"category": "undetected", "result": "unrated", "method": "blacklist", "engine_name": "StopForumSpam"}, "Blueliv": {"category": "undetected", "result": "unrated", "method": "blacklist", "engine_name": "Blueliv"}, "Netcraft": {"category": "undetected", "result": "unrated", "method": "blacklist", "engine_name": "Netcraft"}, "ZeroCERT": {"category": "undetected", "result": "unrated", "method": "blacklist", "engine_name": "ZeroCERT"}, "Phishing Database": {"category": "undetected", "result": "unrated", "method": "blacklist", "engine_name": "Phishing Database"}, "MalwarePatrol": {"category": "undetected", "result": "unrated", "method": "blacklist", "engine_name": "MalwarePatrol"}, "IPsum": {"category": "undetected", "result": "unrated", "method": "blacklist", "engine_name": "IPsum"}, "Malwared": {"category": "undetected", "result": "unrated", "method": "blacklist", "engine_name": "Malwared"}, "BitDefender": {"category": "undetected", "result": "unrated", "method": "blacklist", "engine_name": "BitDefender"}, "GreenSnow": {"category": "undetected", "result": "unrated", "method": "blacklist", "engine_name": "GreenSnow"}, "G-Data": {"category": "undetected", "result": "unrated", "method": "blacklist", "engine_name": "G-Data"}, "VIPRE": {"category": "undetected", "result": "unrated", "method": "blacklist", "engine_name": "VIPRE"}, "SCUMWARE.org": {"category": "undetected", "result": "unrated", "method": "blacklist", "engine_name": "SCUMWARE.org"}, "PhishFort": {"category": "undetected", "result": "unrated", "method": "blacklist", "engine_name": "PhishFort"}, "malwares.com URL checker": {"category": "undetected", "result": "unrated", "method": "blacklist", "engine_name": "malwares.com URL checker"}, "Forcepoint ThreatSeeker": {"category": "undetected", "result": "unrated", "method": "blacklist", "engine_name": "Forcepoint ThreatSeeker"}, "Criminal IP": {"category": "undetected", "result": "unrated", "method": "blacklist", "engine_name": "Criminal IP"}, "Certego": {"category": "undetected", "result": "unrated", "method": "blacklist", "engine_name": "Certego"}, "ESET": {"category": "undetected", "result": "unrated", "method": "blacklist", "engine_name": "ESET"}, "Threatsourcing": {"category": "undetected", "result": "unrated", "method": "blacklist", "engine_name": "Threatsourcing"}, "ThreatHive": {"category": "undetected", "result": "unrated", "method": "blacklist", "engine_name": "ThreatHive"}, "Bfore.Ai PreCrime": {"category": "undetected", "result": "unrated", "method": "blacklist", "engine_name": "Bfore.Ai PreCrime"}}, "last_update_date": 1677456000, "last_modification_date": 1678275436, "tld": "online", "last_https_certificate": {"public_key": {"rsa": {"key_size": 2048, "modulus": "00f2dcf51c1c0b0670cccafd3d6c0b0742538226384b6227662e16814e582ae24c0af99936fe73350a08bf1b16f7df3b1d6bedb613e3ac2ca434a7275fa5fe8f15a0ddd7b8483a00f95f75813d909a67132ad9dbc89bbe1326adcc752fe0a68bf9289156ccb6ab6fa567b1436cb82d81b73b0a4a13a0dccb3f603317ee29bafa43850607b605847ca9c9b1da1eb2491e6320f0b3ebf7f4c3351b45d87a1a99a96c945ed61fb7d20dc845229418aafbb0c447b459419f345dab17ee24b6f462516589daef4317feef813f949f8c5e2e7312617f898e90ec8276993820fcbde94c5ca96090b4cb07546c52e566bf29048933143196dc49b6a29cab439150838a2769", "exponent": "010001"}, "algorithm": "RSA"}, "thumbprint_sha256": "62976530cf1b0c86b954e02cf12316698aff64f622c9abdf45ac5641c97227d1", "tags": [], "signature_algorithm": "sha256RSA", "subject": {"CN": "*.loads19421.online"}, "validity": {"not_after": "2023-05-30 12:22:34", "not_before": "2023-03-01 12:22:35"}, "version": "V3", "extensions": {"certificate_policies": ["2.23.140.1.2.1", "1.3.6.1.4.1.44947.1.1.1"], "extended_key_usage": ["serverAuth", "clientAuth"], "tags": [], "subject_alternative_name": ["*.loads19421.online", "loads19421.online"], "authority_key_identifier": {"keyid": "142eb317b75856cbae500940e61faf9d8b14c2c6"}, "ca_information_access": {"CA Issuers": "http://r3.i.lencr.org/", "OCSP": "http://r3.o.lencr.org"}, "subject_key_identifier": "02a65ce06da4ac7f75bddd135d4eeabc123a24d4", "key_usage": ["ff"], "1.3.6.1.4.1.11129.2.4.2": "0481f100ef007500b73efb24df9c4dba75f239c5ba58f46c5dfc42cf7a9f35c4", "CA": true}, "cert_signature": {"signature_algorithm": "sha256RSA", "signature": "328e7686a40b3b43c6cb2badfc4a1090e7f586ac7e8d52647a81e0d77f510bbce339b7d8395bb25dc696e3f981860d2ee338e0e0940a03346f508abf4c8b3cde2aa0c491989790c7ee612a0b2a49238346963d765e3387606bdff20f3e6263d07b33e628cc2653505d755acc78967acad2fca971598b6fb2485e545768dada85e8f8ff0ea3dbef45cad59d358868f6116de76398f08e304ad0665f8bcea155547a8a48daa5287d6d6555e87ddd2ee3b8a6e4317020cb9e8c7b321cfb65e78127be8c88df81aa9d9343fcbe88bebb22ce79a2a0a30d6e83ee6f389cf70b6eafac4daf7f24192ed1585695a9529b25dd12ee91e658db38ff89f3f452bab4aed7b8"}, "serial_number": "03ea5c30f3598f1c31dc6a811c76e35c4947", "thumbprint": "ca06e27a012765567ba8285ddfed72e212472d30", "issuer": {"C": "US", "CN": "R3", "O": "Let's Encrypt"}, "size": 1346}, "categories": {}, "total_votes": {"harmless": 0, "malicious": 0}}, "type": "domain", "id": "loads19421.online", "links": {"self": "https://www.virustotal.com/api/v3/domains/loads19421.online"}}}