[{"issuer_ca_id": 183267, "issuer_name": "C=US, O=Let's Encrypt, CN=R3", "common_name": "onmi-sg.com", "name_value": "www.onmi-sg.com", "id": 9631331913, "entry_timestamp": "2023-06-12T03:36:43.056", "not_before": "2023-06-12T02:36:42", "not_after": "2023-09-10T02:36:41", "serial_number": "035305ea05013ffec72cc6e27c9dcd5cfc16"}, {"issuer_ca_id": 183267, "issuer_name": "C=US, O=Let's Encrypt, CN=R3", "common_name": "onmi-sg.com", "name_value": "www.onmi-sg.com", "id": 9146060747, "entry_timestamp": "2023-04-13T04:26:43.407", "not_before": "2023-04-13T03:26:42", "not_after": "2023-07-12T03:26:41", "serial_number": "044d9b3756ec2714795e625571ef729644da"}, {"issuer_ca_id": 183267, "issuer_name": "C=US, O=Let's Encrypt, CN=R3", "common_name": "onmi-sg.com", "name_value": "www.onmi-sg.com", "id": 9134031056, "entry_timestamp": "2023-04-13T04:26:43.145", "not_before": "2023-04-13T03:26:42", "not_after": "2023-07-12T03:26:41", "serial_number": "044d9b3756ec2714795e625571ef729644da"}, {"issuer_ca_id": 158800, "issuer_name": "C=AT, O=ZeroSSL, CN=ZeroSSL RSA Domain Secure Site CA", "common_name": "onmi-sg.com", "name_value": "www.onmi-sg.com", "id": 9134811266, "entry_timestamp": "2023-04-13T04:26:23.475", "not_before": "2023-04-13T00:00:00", "not_after": "2023-07-12T23:59:59", "serial_number": "00fcff83e94ffa8a67309ae53a88863c26"}, {"issuer_ca_id": 158800, "issuer_name": "C=AT, O=ZeroSSL, CN=ZeroSSL RSA Domain Secure Site CA", "common_name": "onmi-sg.com", "name_value": "www.onmi-sg.com", "id": 9134811154, "entry_timestamp": "2023-04-13T04:26:22.524", "not_before": "2023-04-13T00:00:00", "not_after": "2023-07-12T23:59:59", "serial_number": "00fcff83e94ffa8a67309ae53a88863c26"}, {"issuer_ca_id": 158800, "issuer_name": "C=AT, O=ZeroSSL, CN=ZeroSSL RSA Domain Secure Site CA", "common_name": "onmi-sg.com", "name_value": "www.onmi-sg.com", "id": 8554072350, "entry_timestamp": "2023-02-01T19:17:40.718", "not_before": "2023-02-01T00:00:00", "not_after": "2023-05-02T23:59:59", "serial_number": "196f017d41b065967764ab052b852907"}, {"issuer_ca_id": 158800, "issuer_name": "C=AT, O=ZeroSSL, CN=ZeroSSL RSA Domain Secure Site CA", "common_name": "onmi-sg.com", "name_value": "www.onmi-sg.com", "id": 8554071896, "entry_timestamp": "2023-02-01T19:17:39.787", "not_before": "2023-02-01T00:00:00", "not_after": "2023-05-02T23:59:59", "serial_number": "196f017d41b065967764ab052b852907"}]